cx_libtranslate/__init__.py
cx_libtranslate/languages.py
cx_libtranslate/loader.py
cx_libtranslate/phrasebook.py
cx_libtranslate/translation.py
cx_libtranslate-1.0.1.dist-info/licenses/LICENSE
cx_libtranslate-1.0.1.dist-info/WHEEL
cx_libtranslate-1.0.1.dist-info/METADATA
cx_libtranslate-1.0.1.dist-info/RECORD
